{"cameraMode":{"drawMode":0,"name":"Shaded","section":"Shading Mode"},"sceneLighting":true,"audioPlay":false,"sceneViewState":{"showFog":true,"showMaterialUpdate":false,"showSkybox":true,"showFlares":true,"showImageEffects":true,"showParticleSystems":true},"in2DMode":false,"pivot":{"x":-115.13204956054688,"y":-68.4573974609375,"z":1444.7960205078125},"rotation":{"x":0.6246781349182129,"y":-0.16476386785507203,"z":0.13706886768341065,"w":0.7508957386016846},"size":275.2276611328125,"orthographic":false}